{
  "name": "TR-909 SP",
  "description": "A 909 kit sampled through an original E-mu SP-1200 sampler, then re-sampled into Maschine ",
  "source": "http://www.flstudiomusic.com/2016/09/download-free-909-kits-stems-f9-audio.html",
  "path": "DM/TR-909/SP/",
  "url": "https://danigb.github.io/sampled/DM/TR-909/SP/",
  "type": "Drum machine",
  "files": {
    "Clap1": "clap1.wav",
    "Clap2": "clap2.wav",
    "Cymbal": "cymbal.wav",
    "Hihat Closed 1": "hihat-closed-1.wav",
    "Hihat Closed 2": "hihat-closed-2.wav",
    "Hihat Open 1": "hihat-open-1.wav",
    "Hihat Open 2": "hihat-open-2.wav",
    "Kick 2": "kick-2.wav",
    "Kick": "kick.wav",
    "Ride": "ride.wav",
    "Rim": "rim.wav",
    "Snare Short": "snare-short.wav",
    "Snare": "snare.wav",
    "Tom H": "tom-h.wav",
    "Tom M": "tom-m.wav",
    "Tom L": "tom-l.wav"
  },
  "samples": "samples/",
  "samplesURL": "https://danigb.github.io/sampled/DM/TR-909/SP/samples/"
}